{
  "theme": {
    "accent": "#c8f542",
    "neon": true
  },
  "projects": [
    {
      "id": "001",
      "tag": "Brand Identity",
      "title": "Studio Nocturn",
      "desc": "Visual identity and website for a creative studio.",
      "thumb": "thumb-1",
      "url": "",
      "image": ""
    },
    {
      "id": "002",
      "tag": "Web Design",
      "title": "Archipelago",
      "desc": "Immersive portfolio for a photographer collective.",
      "thumb": "thumb-2",
      "url": "",
      "image": ""
    },
    {
      "id": "003",
      "tag": "UI / UX",
      "title": "Rumo App",
      "desc": "Direction and discovery tool for independent music.",
      "thumb": "thumb-3",
      "url": "",
      "image": ""
    },
    {
      "id": "004",
      "tag": "Web Design",
      "title": "Verdant Market",
      "desc": "E-commerce experience for a sustainable goods brand.",
      "thumb": "thumb-4",
      "url": "",
      "image": ""
    },
    {
      "id": "005",
      "tag": "Art Direction",
      "title": "Helio Magazine",
      "desc": "Digital editorial design for a culture publication.",
      "thumb": "thumb-5",
      "url": "",
      "image": ""
    },
    {
      "id": "006",
      "tag": "Brand Identity",
      "title": "Solstice Festival",
      "desc": "Campaign identity and digital presence for annual arts fest.",
      "thumb": "thumb-6",
      "url": "",
      "image": ""
    }
  ],
  "skills": [
    {
      "label": "Visual Design",
      "pct": 97
    },
    {
      "label": "Web Development",
      "pct": 82
    },
    {
      "label": "Typography",
      "pct": 91
    },
    {
      "label": "Motion Design",
      "pct": 74
    },
    {
      "label": "Brand Strategy",
      "pct": 68
    }
  ],
  "contact": {
    "phone": "(252) 471-9451",
    "phoneHref": "+12524719451",
    "email": "eduardoquirino290@gmail.com",
    "location": "Rocky Mount, NC, USA"
  },
  "hero": {
    "eyebrow": "Rocky Mount, NC — USA",
    "heading1": "Design that",
    "headingAccent": "moves",
    "heading2": "people.",
    "desc": "A creative studio serving Rocky Mount and the surrounding region — websites, branding, and digital experiences built with care."
  },
  "about": {
    "p1": "Rocky Mount Design Co. is a creative studio based in Rocky Mount, NC. We work with local businesses, nonprofits, and entrepreneurs to build a strong digital presence.",
    "p2": "From custom websites to brand identities, every project is treated with the same care and attention — no templates, no shortcuts.",
    "p3": "Proudly rooted in Rocky Mount. Available locally and remotely across the USA."
  }
}